eagerpy/VERSION
eagerpy/__init__.py
eagerpy/astensor.py
eagerpy/framework.py
eagerpy/lib.py
eagerpy/modules.py
eagerpy/norms.py
eagerpy/py.typed
eagerpy/types.py
eagerpy/utils.py
eagerpy/tensor/__init__.py
eagerpy/tensor/base.py
eagerpy/tensor/extensions.py
eagerpy/tensor/jax.py
eagerpy/tensor/numpy.py
eagerpy/tensor/pytorch.py
eagerpy/tensor/tensor.py
eagerpy/tensor/tensorflow.py
eagerpy-0.30.0.dist-info/LICENSE
eagerpy-0.30.0.dist-info/METADATA
eagerpy-0.30.0.dist-info/WHEEL
eagerpy-0.30.0.dist-info/top_level.txt
eagerpy-0.30.0.dist-info/RECORD
