Metadata-Version: 2.1
Name: eagerpy
Version: 0.30.0
Summary: EagerPy is a thin wrapper around PyTorch, TensorFlow Eager, JAX and NumPy that unifies their interface and thus allows writing code that works natively across all of them.
Home-page: https://github.com/jonasrauber/eagerpy
Author: Jonas Rauber
Author-email: jonas.rauber@bethgelab.org
License: MIT License
Platform: UNKNOWN
Classifier: Development Status :: 3 - Alpha
Classifier: Intended Audience :: Developers
Classifier: Intended Audience :: Science/Research
Classifier: License :: OSI Approved :: MIT License
Classifier: Programming Language :: Python :: 3
Classifier: Programming Language :: Python :: 3.6
Classifier: Topic :: Scientific/Engineering :: Artificial Intelligence
Requires-Dist: numpy
Requires-Dist: typing-extensions (>=3.7.4.1)
Provides-Extra: testing
Requires-Dist: pytest (>=5.3.5) ; extra == 'testing'
Requires-Dist: pytest-cov (>=2.8.1) ; extra == 'testing'
